xoryaml-0.2.0.dist-info/METADATA
xoryaml-0.2.0.dist-info/WHEEL
xoryaml-0.2.0.dist-info/licenses/LICENSE
xoryaml/py.typed
xoryaml/__init__.py
xoryaml/__init__.pyi
xoryaml/xoryaml.cp310-win_amd64.pyd
xoryaml-0.2.0.dist-info/RECORD
