Metadata-Version: 2.4
Name: xoryaml
Version: 0.2.0
Classifier: Programming Language :: Python
Classifier: Programming Language :: Rust
Classifier: Programming Language :: Python :: 3.9
Classifier: Programming Language :: Python :: 3.10
Classifier: Programming Language :: Python :: 3.11
Classifier: Programming Language :: Python :: 3.12
Classifier: Programming Language :: Python :: 3.13
Classifier: Development Status :: 3 - Alpha
Classifier: Operating System :: Microsoft :: Windows
Classifier: Operating System :: POSIX :: Linux
Classifier: Operating System :: MacOS
Classifier: Typing :: Typed
Requires-Dist: pytest ; extra == 'test'
Requires-Dist: tzdata ; extra == 'test'
Requires-Dist: pyyaml ; extra == 'bench'
Requires-Dist: pytest-benchmark ; extra == 'bench'
Requires-Dist: xoryaml[test] ; extra == 'bench'
Provides-Extra: test
Provides-Extra: bench
License-File: LICENSE
Summary: yaml serializer and deserializer backed by yaml_rust2
Keywords: 
Author: jessekv
License: MIT
Requires-Python: >=3.9, <4
Project-URL: homepage, https://github.com/jessekv/xoryaml
Project-URL: repository, https://github.com/jessekv/xoryaml
